Zenith/Builder.py
Zenith/Stylesheet.py
Zenith/Web.py
Zenith/__init__.py
Zenith/lang/ZenithLang.py
Zenith/lang/__init__.py
Zenith/lang/langAST.py
Zenith/lang/langParser.py
Zenith/lang/langTranspiler.py
Zenith/modules/ReadFromZenithFile.py
Zenith/modules/__init__.py
Zenith-Customs/MaterialButton.py
Zenith-Customs/MaterialSlider.py
Zenith-Customs/ZenithDecorator.py
Zenith-Packages/multiport.py
Zenith-Plugins/ToElectron.py
Zenith-Plugins/bugRenderer.py
examples/server.py
zenithlib-1.0.1.dist-info/METADATA
zenithlib-1.0.1.dist-info/WHEEL
zenithlib-1.0.1.dist-info/licenses/LICENSE
zenithlib-1.0.1.dist-info/RECORD
