Metadata-Version: 2.1
Name: ZenithLib
Version: 1.0.1
Summary: Zenith is a powerful Python framework that revolutionizes web development by enabling declarative and efficient UI components for building interactive and scalable websites.
Project-URL: Homepage, https://github.com/Ryan-Rudd/Zenith
Project-URL: Bug Tracker, https://github.com/Ryan-Rudd/Zenith/issues
Author-email: Ryan Rudd <rsrudd@gmail.com>
License-File: LICENSE
Classifier: License :: OSI Approved :: MIT License
Classifier: Operating System :: OS Independent
Classifier: Programming Language :: Python :: 3
Requires-Python: >=3.7
